S3Scanner/S3Bucket.py
S3Scanner/S3Service.py
S3Scanner/__init__.py
S3Scanner/__main__.py
S3Scanner/exceptions.py
S3Scanner-2.0.2.dist-info/LICENSE
S3Scanner-2.0.2.dist-info/METADATA
S3Scanner-2.0.2.dist-info/WHEEL
S3Scanner-2.0.2.dist-info/entry_points.txt
S3Scanner-2.0.2.dist-info/top_level.txt
S3Scanner-2.0.2.dist-info/RECORD
