Metadata-Version: 2.1
Name: S3Scanner
Version: 2.0.2
Summary: Scan for open S3 buckets and dump the contents
Home-page: https://github.com/sa7mon/S3Scanner
Author: Dan Salmon
Author-email: dan@salmon.cat
License: UNKNOWN
Project-URL: Bug Tracker, https://github.com/sa7mon/S3Scanner
Platform: UNKNOWN
Classifier: Programming Language :: Python :: 3.6
Classifier: Programming Language :: Python :: 3.7
Classifier: Programming Language :: Python :: 3.8
Classifier: Programming Language :: Python :: 3.9
Classifier: Topic :: Security
Classifier: License :: OSI Approved :: MIT License
Classifier: Operating System :: OS Independent
Requires-Python: >=3.6
License-File: LICENSE
Requires-Dist: boto3 (>=1.20)
